[{"title":"浏览专属配件频道","mes_1":"保护壳","mes_2":"贴膜","mes_3":"盒子专属配件","mes_4":"表带","mes_5":"","mes_6":"","mes_7":"","mes_8":"","child":[{"img":"images/index/428_428_1473406494708mp.jpg","name":"HUAWEI Mate 10 手机导航套件","money":"￥199"},{"img":"images/index/428_428_1473406494708mp.jpg","name":"HUAWEI Mate 10 手机导航套件","money":"￥199"},{"img":"images/index/428_428_1473406494708mp.jpg","name":"HUAWEI Mate 10 手机导航套件","money":"￥199"},{"img":"images/index/428_428_1473406494708mp.jpg","name":"HUAWEI Mate 10 手机导航套件","money":"￥199"}]}]